setup.cfg
setup.py
django_telegram.egg-info/PKG-INFO
django_telegram.egg-info/SOURCES.txt
django_telegram.egg-info/dependency_links.txt
django_telegram.egg-info/entry_points.txt
django_telegram.egg-info/not-zip-safe
django_telegram.egg-info/requires.txt
django_telegram.egg-info/top_level.txt
telegram/__init__.py
telegram/admin.py
telegram/api.py
telegram/decorators.py
telegram/exceptions.py
telegram/forms.py
telegram/models.py
telegram/tasks.py
telegram/tests.py
telegram/urls.py
telegram/views.py
telegram/handlers/__init__.py
telegram/handlers/base.py
telegram/handlers/dummy.py
telegram/handlers/email.py
telegram/handlers/webservice.py
telegram/management/__init__.py
telegram/management/commands/__init__.py
telegram/management/commands/createchannel.py
telegram/management/commands/createplatform.py
telegram/management/commands/removechannel.py
telegram/utils/__init__.py