Metadata-Version: 1.0
Name: django-telegram
Version: 0.1.0dev
Summary: A messaging framework that supports email, irc, notify my android and others
Home-page: UNKNOWN
Author: Kyle Terry
Author-email: kyle@kyleterry.com
License: UNKNOWN
Keywords: messaging,push,django
Platform: UNKNOWN
